colprint/__init__.py
colprint/cprint.py
colprint-0.0.1.dist-info/METADATA
colprint-0.0.1.dist-info/RECORD
colprint-0.0.1.dist-info/WHEEL
colprint-0.0.1.dist-info/entry_points.txt
colprint-0.0.1.dist-info/top_level.txt
