Metadata-Version: 2.1
Name: colprint
Version: 0.0.1
Summary: for simply print some colorful hints
Home-page: https://github.com/alanzhchou/python_utils/tree/master/colprint
Author: alanzhchou
Author-email: alanzhchou@gmail.com
License: UNKNOWN
Platform: UNKNOWN
